{"base_path":"/","components":null,"consumes":"","definitions":{"ErrorResponseBody":{"properties":{"error_code":{"description":"错误码","example":"CB.00060200","type":"string"},"error_msg":{"description":"错误描述","example":"Invalid param","type":"string"}},"type":"object"},"TotalResponseBody":{"properties":{"error":{"description":"错误","type":"object"},"result":{"description":"结果","properties":{"total":{"description":"总数","example":100,"type":"integer"}}},"status":{"description":"状态信息","example":"success","type":"string"}},"title":"recoverBuildJobResponseBody","type":"object"}},"description":null,"group_id":"50626d0f704e4af3adfd875e2acffcb6","host":"cloudbuild-ext.cn-north-4.myhuaweicloud.com","id":"91d42629e587400b8f49c2b4d4515d9f","info_version":"v3","method":"get","name":"ShowJobTotal","parameters":{"Build_Project_Id":{"description":"构建工程项目ID,36位数字、小写字母组合。","in":"path","name":"build_project_id","pattern":"^[0-9a-z]{36}$","required":true,"type":"string","x-example":"ee24b7bf-0285-43b4-b975-77f615884466"}},"paths":{"/v1/record/{build_project_id}/statistics":{"get":{"deprecated":false,"description":"构建历史页获取构建次数","operationId":"ShowJobTotal","parameters":[{"$ref":"#/parameters/Build_Project_Id"},{"description":"区间开始时间,格式yyyy-MM-dd HH:mm:ss。","in":"query","name":"from_date","required":false,"type":"string"},{"description":"区间结束时间,格式yyyy-MM-dd HH:mm:ss。","in":"query","name":"to_date","required":false,"type":"string"}],"produces":["application/json;charset=UTF-8"],"responses":{"200":{"description":"OK","examples":{"application/json":{"error":null,"result":{"total":9},"status":"success"}},"schema":{"$ref":"#/definitions/TotalResponseBody"}},"400":{"description":"Bad Request","schema":{"$ref":"#/definitions/ErrorResponseBody"}},"401":{"description":"Unauthorized","schema":{"$ref":"#/definitions/ErrorResponseBody"}},"403":{"description":"Forbidden","schema":{"$ref":"#/definitions/ErrorResponseBody"}},"404":{"description":"Not Found","schema":{"$ref":"#/definitions/ErrorResponseBody"}},"500":{"description":"Internal Server Error","schema":{"$ref":"#/definitions/ErrorResponseBody"}}},"security":[{"apig-auth-iam":[]}],"summary":"构建历史页获取构建次数","tags":["RecordManager"],"x-api-type":"open-api","x-apigateway-ratelimit":"ten_50_min","x-internel":"false","x-is-registered":"Y","x-request-examples-url-1":"GET https://{endpoint}/v1/record/157010e7-1d62-481d-b205-5eaf2c65d339/statistics","x-support-sdk":"Y"}}},"product_short":"CodeArtsBuild","region_id":"cn-north-4","schemes":["HTTPS"],"security_definitions":{"APP":{"in":"header","name":"Authorization","type":"apiKey","x-apigateway-auth-type":"AppSigv1"},"apig-auth-app-optional":{"in":"header","name":"Authorization","type":"apiKey","x-apigateway-auth-opt":{"access-auth-type":"optional"},"x-apigateway-auth-type":"AppSigv1"},"apig-auth-iam":{"in":"header","name":"unused","type":"apiKey","x-apigateway-auth-type":"IAM"},"apig-auth-iam-none":{"in":"header","name":"unused","type":"apiKey","x-apigateway-auth-type":"IAM_NONE"}},"summary":"构建历史页获取构建次数","tags":"构建记录","uri":null,"version":"2.0"}