{"base_path":null,"components":{"parameters":{"ManagedOrganizationUnitId":{"description":"注册OU ID。","in":"path","name":"managed_organization_unit_id","required":true,"schema":{"maxLength":64,"pattern":"^ou-[0-9a-z]{8,32}$|^r-[0-9a-z]{8,32}$","type":"string"}}}},"consumes":"","definitions":null,"description":null,"group_id":"145991efb91f4735802bb0e92af52583","host":"rgc.cn-north-4.myhuaweicloud.com","id":"7ee8322257064439b95e613600fb8dbb","info_version":"v1","method":"delete","name":"DeleteManagedOrganizationalUnits","parameters":null,"paths":{"/v1/managed-organization/managed-organization-units/{managed_organization_unit_id}":{"delete":{"description":"在组织里删除已注册OU。","operationId":"DeleteManagedOrganizationalUnits","parameters":[{"$ref":"#/components/parameters/ManagedOrganizationUnitId"}],"responses":{"204":{"description":"请求成功。"}},"security":[{"AccessKeyAuth":[]}],"summary":"删除注册OU","tags":["ManagedOrganization"],"x-is-registered":"Y","x-request-examples-description-1":"在组织里删除已注册OU。","x-request-examples-url-1":"DELETE https://{hostname}/v1/managed-organization/managed-organization-units/{managed_organization_unit_id}","x-support-sdk":"Y"}}},"product_short":"RGC","region_id":"cn-north-4","schemes":["HTTPS"],"security_definitions":null,"summary":"删除注册OU","tags":"组织管理","uri":null,"version":"3.0.3"}