{"base_path":null,"components":{"parameters":{"DomainIdInPath":{"description":"path中租户的账号ID","in":"path","name":"domain_id","required":true,"schema":{"maxLength":36,"type":"string"}},"EdgeSiteIdInPath":{"description":"边缘小站ID","in":"path","name":"site_id","required":true,"schema":{"pattern":"[a-fA-F0-9]{8}-[a-fA-F0-9]{4}-[a-fA-F0-9]{4}-[a-fA-F0-9]{4}-[a-fA-F0-9]{12}","type":"string"}},"XAuthToken":{"description":"用户Token","in":"header","name":"X-Auth-Token","required":true,"schema":{"type":"string"}}},"schemas":{"Condition":{"description":"场地条件","maxLength":1024,"properties":{"environment":{"default":0,"description":"机房环境条件\n取值范围:\n  - 0:机房条件不属于上述任何一种情况\n  - 1:机房使用模块化数据中心方案进行建设\n  - 2:机房已通过国家级或行业级标准化认证","format":"int32","maximum":2,"minimum":0,"type":"integer"},"installation":{"default":"UNCLEAR","description":"整柜安装评估\n取值范围:\n  - UNCLEAR:不清楚是否允许整柜安装,需要评估\n  - UNSUPPORT:不允许整柜安装,需将设备放入现有机柜\n  - SUPPORT:可支持整柜安装,并入现有机柜组","enum":["UNCLEAR","UNSUPPORT","SUPPORT"],"type":"string"},"space":{"default":0,"description":"机柜空间条件\n取值范围:\n  - 0:暂无扩容计划,不考虑额外余量\n  - 1:机柜余量相对充裕,可放置空间超过3柜\n  - 2:机柜余量相对紧张,可放置空间3柜以内","format":"int32","maximum":2,"minimum":0,"type":"integer"},"transport":{"default":0,"description":"运输条件\n取值范围:\n  - 0:运输通道和机房门的高度或宽度不满足要求\n  - 1:运输通道,货梯,机房门均可满足整机柜滚轮搬运\n  - 2:运输通道,货梯,机房门不能支持整机柜滚轮搬运,沿途有台阶","format":"int32","maximum":2,"minimum":0,"type":"integer"}},"type":"object"},"EdgeSiteDetail":{"description":"边缘小站详情","properties":{"availability_zone_id":{"description":"边缘小站的可用区ID","type":"string"},"created_at":{"description":"边缘小站创建时间","format":"date-time","type":"string"},"description":{"description":"边缘小站描述","type":"string"},"domain_id":{"description":"边缘小站所属账号ID","type":"string"},"enterprise_project_id":{"description":"边缘小站所属企业项目ID","type":"string"},"id":{"description":"边缘小站ID","type":"string"},"location":{"$ref":"#/components/schemas/LocationDetail"},"name":{"description":"边缘小站名称","type":"string"},"project_id":{"description":"边缘小站所属项目ID","type":"string"},"region_id":{"description":"边缘小站所属区域ID","type":"string"},"status":{"description":"边缘小站的部署状态","type":"string"},"updated_at":{"description":"边缘小站更新时间","format":"date-time","type":"string"}},"type":"object"},"LocationDetail":{"description":"场地详情","properties":{"address":{"description":"部署位置","type":"string"},"city":{"description":"场地所在市/区","type":"string"},"condition":{"$ref":"#/components/schemas/Condition","description":"场地条件"},"country":{"description":"场地所在国家(逐步下线,使用zone_code替代)","type":"string"},"description":{"description":"场地描述","type":"string"},"district":{"description":"场地所在区/县","type":"string"},"name":{"deprecated":true,"description":"场地名称(已废弃),传入该参数不会再生效,新建站点也不会再返回该字段","type":"string"},"province":{"description":"场地所在省/自治区/直辖市","type":"string"},"zone_code":{"description":"场地所在地区","type":"string"}},"type":"object"},"UpdateCondition":{"description":"场地条件","maxLength":1024,"properties":{"environment":{"description":"机房环境条件\n取值范围:\n  - 0:机房条件不属于上述任何一种情况\n  - 1:机房使用模块化数据中心方案进行建设\n  - 2:机房已通过国家级或行业级标准化认证","format":"int32","maximum":2,"minimum":0,"type":"integer"},"installation":{"description":"整柜安装评估\n取值范围:\n  - UNCLEAR:不清楚是否允许整柜安装,需要评估\n  - UNSUPPORT:不允许整柜安装,需将设备放入现有机柜\n  - SUPPORT:可支持整柜安装,并入现有机柜组","enum":["UNCLEAR","UNSUPPORT","SUPPORT"],"type":"string"},"space":{"description":"机柜空间条件\n  - 0:暂无扩容计划,不考虑额外余量\n  - 1:机柜余量相对充裕,可放置空间超过3柜\n  - 2:机柜余量相对紧张,可放置空间3柜以内","format":"int32","maximum":2,"minimum":0,"type":"integer"},"transport":{"description":"运输条件\n取值范围:\n  - 0:运输通道和机房门的高度或宽度不满足要求\n  - 1:运输通道,货梯,机房门均可满足整机柜滚轮搬运\n  - 2:运输通道,货梯,机房门不能支持整机柜滚轮搬运,沿途有台阶","format":"int32","maximum":2,"minimum":0,"type":"integer"}},"type":"object"},"UpdateEdgeSite":{"properties":{"description":{"description":"边缘小站描述,最大支持长度为255个字节,不允许包含<>","maxLength":255,"pattern":"[^<>]*","type":"string"},"location":{"$ref":"#/components/schemas/UpdateLocation","description":"场地信息"}},"type":"object"},"UpdateEdgeSiteRequestBody":{"properties":{"edge_site":{"$ref":"#/components/schemas/UpdateEdgeSite","description":"待更新的边缘小站参数"}},"required":["edge_site"],"type":"object"},"UpdateEdgeSiteResponseBody":{"properties":{"edge_site":{"$ref":"#/components/schemas/EdgeSiteDetail"}},"type":"object"},"UpdateLocation":{"description":"场地信息","properties":{"city":{"description":"场地所在市/区","maxLength":64,"minLength":1,"pattern":"[^<>]*","type":"string"},"condition":{"$ref":"#/components/schemas/UpdateCondition","description":"场地条件"},"country":{"description":"场地所在国家","enum":["CN"],"type":"string"},"description":{"description":"场地描述,最大支持长度为255个字节,不允许包含<>","maxLength":255,"pattern":"[^<>]*","type":"string"},"district":{"description":"场地所在区/县","maxLength":64,"minLength":1,"pattern":"[^<>]*","type":"string"},"name":{"deprecated":true,"description":"场地名称(已废弃),传入该参数不会再生效,新建站点也不会再返回该字段","type":"string"},"province":{"description":"场地所在省/自治区/直辖市","maxLength":64,"minLength":1,"pattern":"[^<>]*","type":"string"}},"type":"object"}}},"consumes":"","definitions":null,"description":null,"group_id":"f0980c7f651d49b4942bf02104fcd741","host":"ies.myhuaweicloud.com","id":"2dc4b489c8344592a5e0ba3c7a368ce8","info_version":"v1","method":"put","name":"UpdateEdgeSite","parameters":null,"paths":{"/v1/{domain_id}/edge-sites/{site_id}":{"put":{"description":"更新边缘小站。\n- 允许更新边缘小站描述或场地信息。","operationId":"UpdateEdgeSite","parameters":[{"$ref":"#/components/parameters/XAuthToken"},{"$ref":"#/components/parameters/DomainIdInPath"},{"$ref":"#/components/parameters/EdgeSiteIdInPath"}],"requestBody":{"content":{"application/json":{"schema":{"$ref":"#/components/schemas/UpdateEdgeSiteRequestBody"}}},"description":"请求参数对象","required":true},"responses":{"200":{"content":{"application/json":{"example":{"edge_site":{"availability_zone_id":null,"created_at":"2022-04-15T07:59:20.641Z","description":"测试站点:位于安徽","domain_id":"2b76febbe5d34eac85d26435c1f15809","id":"cc89b1e5-521d-4a85-be83-e6f7217fc63e","location":{"address":"安徽省 合肥市 瑶海区","city":"合肥市","condition":{"environment":0,"installation":"SUPPORT","space":0,"transport":0},"description":"测试站点场地信息","district":"瑶海区","province":"安徽省","zone_code":"CN"},"name":"测试站点","project_id":"060576838600d5762f2dc000470eb164","region_id":"cn-north-4","status":"initial","updated_at":"2022-04-15T08:59:20.641Z"}},"schema":{"$ref":"#/components/schemas/UpdateEdgeSiteResponseBody"}}},"description":"successful operation"}},"summary":"更新边缘小站","tags":["edge-site"],"x-is-registered":"Y","x-open-region-cloud":"hc,hk","x-request-examlpes-text-1":"{\n  \"edge_site\": {\n      \"description\": \"测试站点:位于安徽\",\n      \"location\": {\n          \"description\": \"测试站点场地信息\",\n          \"zone_code\": \"CN\",\n          \"address\": \"安徽省 合肥市 瑶海区\",\n          \"province\": \"安徽省\",\n          \"city\": \"合肥市\",\n          \"district\": \"瑶海区\",\n          \"condition\": {\n              \"environment\": 0,\n              \"space\": 0,\n              \"transport\": 0,\n              \"installation\": \"SUPPORT\"\n          }\n      }\n  }\n}","x-request-examples-1":{"edge_site":{"description":"测试站点:位于安徽","location":{"city":"合肥市","condition":{"environment":0,"installation":"SUPPORT","space":0,"transport":0},"country":"CN","description":"测试站点场地信息","district":"瑶海区","province":"安徽省"}}},"x-request-examples-description-1":"更新边缘小站","x-request-examples-url-1":"PUT https://{ies_endpoint}/v1/{domain_id}/edge-sites/{site_id}","x-support-sdk":"Y"}}},"product_short":"CloudPond","region_id":"cn-north-4","schemes":["HTTPS"],"security_definitions":null,"summary":"更新边缘小站","tags":"边缘小站","uri":null,"version":"3.0.0"}