{"base_path":null,"components":null,"consumes":"[\"application/json;charset=UTF-8\",\"application/json\"]","definitions":{"RegisterVoiceReq":{"properties":{"config":{"description":"配置信息","properties":{"language":{"description":"data中语音数据的语种,取值chinese、english。\n默认是chinese。","type":"string"},"voice_name":{"description":"注册声音的名称,不能以数字、下划线开头。仅包含大、小写英文字母、数字和下划线,且长度不超过20个字符。一个project id下的声音名称不能重复。","type":"string"}},"required":["voice_name"]},"data":{"description":"录音数据,使用base64编码,大小不超过6MB。支持wav、mp3、m4a格式,采样率不小于16kHz,时长在5-25秒,支持单、双通道。","type":"string"}},"required":["config","data"],"type":"object"},"RegisterVoiceResponseBody":{"properties":{"result":{"description":"注册声音响应。","properties":{"voice_name":{"description":"注册声音的名称。","type":"string"}},"type":"object"},"trace_id":{"description":"服务内部的令牌,可用于在日志中追溯具体流程。","type":"string"}},"required":["trace_id","result"],"type":"object"},"vcsErrorResp":{"description":"Internal Server Error","properties":{"error_code":{"description":"调用失败时的错误码。\n调用成功时无此字段。","type":"string"},"error_msg":{"description":"调用失败时的错误信息。\n调用成功时无此字段。","type":"string"}},"type":"object"}},"description":null,"group_id":"9de3af80b8dd488598624403f5e27d74","host":"sis-ext.cn-north-4.myhuaweicloud.com","id":"54186bc7ae234e6b835dc3053f4831b6","info_version":"v1","method":"post","name":"CreateVoice","parameters":{},"paths":{"/v1/{project_id}/vcs/voices":{"post":{"description":"客户上传一段录音,并指定voice_name,在系统中注册声音。","operationId":"CreateVoice","parameters":[{"description":"来自公有云的Project ID,用于资源隔离。","in":"path","name":"project_id","required":true,"type":"string"},{"description":"请求体","in":"body","name":"CreateVoiceRequestBody","required":true,"schema":{"$ref":"#/definitions/RegisterVoiceReq"}},{"description":"用户Token。","in":"header","name":"X-Auth-Token","required":true,"type":"string"}],"responses":{"200":{"description":"注册声音成功","examples":{"application/json":{"result":{"voice_name":"chinese_xiaoming_xxxxxxxxxx"},"trace_id":"567e8537-a89c-13c3-a882-826321939651"}},"schema":{"$ref":"#/definitions/RegisterVoiceResponseBody"}},"400":{"description":"","schema":{"$ref":"#/definitions/vcsErrorResp"}},"401":{"description":"Unauthorized","examples":{"application/json":{"error_code":"SIS.0101","error_msg":"auth failed, please check if token correct"}},"schema":{"$ref":"#/definitions/vcsErrorResp"}},"500":{"description":"Internal Server Error","examples":{"application/json":{"error_code":"SIS.0100","error_msg":"inner service exception"}},"schema":{"$ref":"#/definitions/vcsErrorResp"}}},"summary":"注册接口","tags":["声音复刻接口"],"x-api-type":"open-api","x-apiexplorer-hide":"N","x-is-registered":"Y","x-open-region-cloud":"hc","x-request-examples-1":{"config":{"language":"chinese","voice_name":"test_001"},"data":"d+++++++"},"x-request-examples-text-1":{"config":{"language":"chinese","voice_name":"test_001"},"data":"d+++++++"},"x-request-examples-url-1":"https://{endpoint}//v1/{project_id}/vcs/voices","x-support-sdk":"Y"}}},"product_short":"SIS","region_id":"cn-north-4","schemes":["HTTPS"],"security_definitions":null,"summary":"注册接口","tags":"声音复刻接口","uri":null,"version":"2.0"}